sounds/__init__.py
sounds/architecture.s.HTML
sounds/license.S.HTML
sounds/module.MD
sounds/module.s.HTML
sounds/__agenda/agenda.S.HTML
sounds/__agenda/maybes.s.HTML
sounds/__agenda/processes/errout/script.py
sounds/__agenda/processes/errout/start.py
sounds/__agenda/processes/errout_v1/script.py
sounds/__agenda/processes/errout_v1/start.py
sounds/__agenda/processes/errout_v2/script.py
sounds/__agenda/processes/errout_v2/start.py
sounds/_book/advanced tutorial.s.HTML
sounds/_book/book.s.HTML
sounds/_book/example output.s.HTML
sounds/_book/relevant.s.HTML
sounds/_clique/__init__.py
sounds/_clique/group/__init__.py
sounds/_status/establish.py
sounds/_status/status.proc.py
sounds/_status/status.s.HTML
sounds/_status/status_py.py
sounds/_status/DB/records.json
sounds/_status/monitors/-1_start/status_1.py
sounds/_status/monitors/-1_start/chassis/modules/monitor_1.py
sounds/_status/monitors/0_start/status_1.py
sounds/_status/monitors/0_start/chassis/modules/monitor_1.py
sounds/_status/monitors/1/status_1.py
sounds/_status/monitors/1/stasis/path_1_health.py
sounds/_status/monitors/1/stasis/path_2_health.py
sounds/_status/monitors/2/status_1.py
sounds/_status/monitors/2/stasis/1_health.py
sounds/_status/monitors/2/stasis/2_health.py
sounds/_status/monitors/2/stasis/modules/MODULE_1.py
sounds/_status/monitors/3_empty_glob/status_1.py
sounds/_status/monitors/4_bad_import/status_1.py
sounds/_status/monitors/4_bad_import/stasis/1_health.py
sounds/_status/monitors/5__file__/status_1.py
sounds/_status/monitors/5__file__/stasis/1_health.py
sounds/_status/monitors/5__file__/stasis/MODULES/MODULE_1.py
sounds/_status/monitors/6_various/status_1.py
sounds/_status/monitors/6_various/stasis/1_health.py
sounds/_status/monitors/6_various/stasis/2_health.py
sounds/_status/monitors/6_various/stasis/3_health.py
sounds/_status/monitors/6_various/stasis/MODULES/MODULE_1.py
sounds/_status/monitors/7/status_1.py
sounds/_status/monitors/7/stasis/guarantee_1.py
sounds-1.0.0.dist-info/METADATA
sounds-1.0.0.dist-info/WHEEL
sounds-1.0.0.dist-info/entry_points.txt
sounds-1.0.0.dist-info/top_level.txt
sounds-1.0.0.dist-info/RECORD
